{
  "number": 70,
  "latinName": "Al-Ma‘ārij",
  "arabicName": "المعارج",
  "totalAyat": 44,
  "ayahs": [
    {
      "numberInSurah": 1,
      "numberGlobal": 5376,
      "arabic": "سَاَلَ سَاۤىِٕلٌۢ بِعَذَابٍ وَّاقِعٍۙ",
      "translation": "Seseorang (dengan nada mengejek) meminta (didatangkan) azab yang pasti akan terjadi"
    },
    {
      "numberInSurah": 2,
      "numberGlobal": 5377,
      "arabic": "لِّلْكٰفِرِيْنَ لَيْسَ لَهٗ دَافِعٌۙ",
      "translation": "bagi orang-orang kafir. Tidak seorang pun yang dapat menolaknya (azab)"
    },
    {
      "numberInSurah": 3,
      "numberGlobal": 5378,
      "arabic": "مِّنَ اللّٰهِ ذِى الْمَعَارِجِۗ",
      "translation": "dari Allah, Pemilik tempat-tempat (untuk) naik."
    },
    {
      "numberInSurah": 4,
      "numberGlobal": 5379,
      "arabic": "تَعْرُجُ الْمَلٰۤىِٕكَةُ وَالرُّوْحُ اِلَيْهِ فِيْ يَوْمٍ كَانَ مِقْدَارُهٗ خَمْسِيْنَ اَلْفَ سَنَةٍۚ",
      "translation": "Para malaikat dan Rūḥ (Jibril) naik (menghadap) kepada-Nya dalam sehari yang kadarnya lima puluh ribu tahun.722)"
    },
    {
      "numberInSurah": 5,
      "numberGlobal": 5380,
      "arabic": "فَاصْبِرْ صَبْرًا جَمِيْلًا",
      "translation": "Maka, bersabarlah dengan kesabaran yang baik."
    },
    {
      "numberInSurah": 6,
      "numberGlobal": 5381,
      "arabic": "اِنَّهُمْ يَرَوْنَهٗ بَعِيْدًاۙ",
      "translation": "Sesungguhnya mereka memandangnya (siksaan itu) jauh (mustahil terjadi),"
    },
    {
      "numberInSurah": 7,
      "numberGlobal": 5382,
      "arabic": "وَّنَرٰىهُ قَرِيْبًاۗ",
      "translation": "sedangkan Kami memandangnya dekat (pasti terjadi)."
    },
    {
      "numberInSurah": 8,
      "numberGlobal": 5383,
      "arabic": "يَوْمَ تَكُوْنُ السَّمَاۤءُ كَالْمُهْلِۙ",
      "translation": "(Siksaan itu datang) pada hari (ketika) langit menjadi seperti luluhan perak,"
    },
    {
      "numberInSurah": 9,
      "numberGlobal": 5384,
      "arabic": "وَتَكُوْنُ الْجِبَالُ كَالْعِهْنِۙ",
      "translation": "gunung-gunung menjadi seperti bulu (yang beterbangan),"
    },
    {
      "numberInSurah": 10,
      "numberGlobal": 5385,
      "arabic": "وَلَا يَسْـَٔلُ حَمِيْمٌ حَمِيْمًاۚ",
      "translation": "dan tidak ada seorang pun teman setia yang menanyakan temannya,"
    },
    {
      "numberInSurah": 11,
      "numberGlobal": 5386,
      "arabic": "يُبَصَّرُوْنَهُمْۗ يَوَدُّ الْمُجْرِمُ لَوْ يَفْتَدِيْ مِنْ عَذَابِ يَوْمِىِٕذٍۢ بِبَنِيْهِۙ",
      "translation": "(padahal) mereka saling melihat. Orang yang berbuat durhaka itu menginginkan sekiranya dia dapat menebus (dirinya) dari azab hari itu dengan anak-anaknya,"
    },
    {
      "numberInSurah": 12,
      "numberGlobal": 5387,
      "arabic": "وَصَاحِبَتِهٖ وَاَخِيْهِۙ",
      "translation": "istrinya, saudaranya,"
    },
    {
      "numberInSurah": 13,
      "numberGlobal": 5388,
      "arabic": "وَفَصِيْلَتِهِ الَّتِيْ تُـْٔوِيْهِۙ",
      "translation": "keluarga yang melindunginya (di dunia),"
    },
    {
      "numberInSurah": 14,
      "numberGlobal": 5389,
      "arabic": "وَمَنْ فِى الْاَرْضِ جَمِيْعًاۙ ثُمَّ يُنْجِيْهِۙ",
      "translation": "dan seluruh orang di bumi. Kemudian, (dia mengharapkan) tebusan itu dapat menyelamatkannya."
    },
    {
      "numberInSurah": 15,
      "numberGlobal": 5390,
      "arabic": "كَلَّاۗ اِنَّهَا لَظٰىۙ",
      "translation": "Sekali-kali tidak! Sesungguhnya ia (neraka) itu adalah api yang bergejolak"
    },
    {
      "numberInSurah": 16,
      "numberGlobal": 5391,
      "arabic": "نَزَّاعَةً لِّلشَّوٰىۚ",
      "translation": "yang mengelupaskan kulit kepala,"
    },
    {
      "numberInSurah": 17,
      "numberGlobal": 5392,
      "arabic": "تَدْعُوْا مَنْ اَدْبَرَ وَتَوَلّٰىۙ",
      "translation": "yang memanggil orang yang berpaling dan menjauh (dari agama),"
    },
    {
      "numberInSurah": 18,
      "numberGlobal": 5393,
      "arabic": "وَجَمَعَ فَاَوْعٰى",
      "translation": "serta mengumpulkan (harta benda), lalu menyimpannya.723)"
    },
    {
      "numberInSurah": 19,
      "numberGlobal": 5394,
      "arabic": "۞ اِنَّ الْاِنْسَانَ خُلِقَ هَلُوْعًاۙ",
      "translation": "Sesungguhnya manusia diciptakan dengan sifat keluh kesah lagi kikir."
    },
    {
      "numberInSurah": 20,
      "numberGlobal": 5395,
      "arabic": "اِذَا مَسَّهُ الشَّرُّ جَزُوْعًاۙ",
      "translation": "Apabila ditimpa keburukan (kesusahan), ia berkeluh kesah."
    },
    {
      "numberInSurah": 21,
      "numberGlobal": 5396,
      "arabic": "وَّاِذَا مَسَّهُ الْخَيْرُ مَنُوْعًاۙ",
      "translation": "Apabila mendapat kebaikan (harta), ia amat kikir,"
    },
    {
      "numberInSurah": 22,
      "numberGlobal": 5397,
      "arabic": "اِلَّا الْمُصَلِّيْنَۙ",
      "translation": "kecuali orang-orang yang mengerjakan salat,"
    },
    {
      "numberInSurah": 23,
      "numberGlobal": 5398,
      "arabic": "الَّذِيْنَ هُمْ عَلٰى صَلَاتِهِمْ دَاۤىِٕمُوْنَۖ",
      "translation": "yang selalu setia mengerjakan salatnya,"
    },
    {
      "numberInSurah": 24,
      "numberGlobal": 5399,
      "arabic": "وَالَّذِيْنَ فِيْٓ اَمْوَالِهِمْ حَقٌّ مَّعْلُوْمٌۖ",
      "translation": "yang di dalam hartanya ada bagian tertentu"
    },
    {
      "numberInSurah": 25,
      "numberGlobal": 5400,
      "arabic": "لِّلسَّاۤىِٕلِ وَالْمَحْرُوْمِۖ",
      "translation": "untuk orang (miskin) yang meminta-minta dan orang (miskin) yang menahan diri dari meminta-minta,"
    },
    {
      "numberInSurah": 26,
      "numberGlobal": 5401,
      "arabic": "وَالَّذِيْنَ يُصَدِّقُوْنَ بِيَوْمِ الدِّيْنِۖ",
      "translation": "yang memercayai hari Pembalasan,"
    },
    {
      "numberInSurah": 27,
      "numberGlobal": 5402,
      "arabic": "وَالَّذِيْنَ هُمْ مِّنْ عَذَابِ رَبِّهِمْ مُّشْفِقُوْنَۚ",
      "translation": "dan yang takut terhadap azab Tuhannya."
    },
    {
      "numberInSurah": 28,
      "numberGlobal": 5403,
      "arabic": "اِنَّ عَذَابَ رَبِّهِمْ غَيْرُ مَأْمُوْنٍۖ",
      "translation": "Sesungguhnya tidak ada orang yang merasa aman dari azab Tuhan mereka."
    },
    {
      "numberInSurah": 29,
      "numberGlobal": 5404,
      "arabic": "وَّالَّذِيْنَ هُمْ لِفُرُوْجِهِمْ حٰفِظُوْنَۙ",
      "translation": "(Termasuk orang yang selamat dari azab adalah) orang-orang yang menjaga kemaluannya,"
    },
    {
      "numberInSurah": 30,
      "numberGlobal": 5405,
      "arabic": "اِلَّا عَلٰٓى اَزْوَاجِهِمْ اَوْ مَا مَلَكَتْ اَيْمَانُهُمْ فَاِنَّهُمْ غَيْرُ مَلُوْمِيْنَۚ",
      "translation": "kecuali terhadap istri-istri mereka atau hamba sahaya yang mereka miliki.724) Sesungguhnya mereka tidak tercela (karena menggaulinya)."
    },
    {
      "numberInSurah": 31,
      "numberGlobal": 5406,
      "arabic": "فَمَنِ ابْتَغٰى وَرَاۤءَ ذٰلِكَ فَاُولٰۤىِٕكَ هُمُ الْعَادُوْنَۚ",
      "translation": "Maka, siapa yang mencari (pelampiasan syahwat) selain itu, mereka itulah orang-orang yang melampaui batas."
    },
    {
      "numberInSurah": 32,
      "numberGlobal": 5407,
      "arabic": "وَالَّذِيْنَ هُمْ لِاَمٰنٰتِهِمْ وَعَهْدِهِمْ رٰعُوْنَۖ",
      "translation": "(Termasuk orang yang selamat dari azab adalah) orang-orang yang memelihara amanat dan janji mereka,"
    },
    {
      "numberInSurah": 33,
      "numberGlobal": 5408,
      "arabic": "وَالَّذِيْنَ هُمْ بِشَهٰدٰتِهِمْ قَاۤىِٕمُوْنَۖ",
      "translation": "yang memberikan kesaksiannya (secara benar),"
    },
    {
      "numberInSurah": 34,
      "numberGlobal": 5409,
      "arabic": "وَالَّذِيْنَ هُمْ عَلٰى صَلَاتِهِمْ يُحَافِظُوْنَۖ",
      "translation": "dan yang memelihara salatnya."
    },
    {
      "numberInSurah": 35,
      "numberGlobal": 5410,
      "arabic": "اُولٰۤىِٕكَ فِيْ جَنّٰتٍ مُّكْرَمُوْنَ ۗ ࣖ",
      "translation": "Mereka itu (berada) di surga lagi dimuliakan."
    },
    {
      "numberInSurah": 36,
      "numberGlobal": 5411,
      "arabic": "فَمَالِ الَّذِيْنَ كَفَرُوْا قِبَلَكَ مُهْطِعِيْنَۙ",
      "translation": "Mengapa orang-orang kafir itu bersegera datang ke arahmu (Nabi Muhammad)"
    },
    {
      "numberInSurah": 37,
      "numberGlobal": 5412,
      "arabic": "عَنِ الْيَمِيْنِ وَعَنِ الشِّمَالِ عِزِيْنَ",
      "translation": "dari kanan dan dari kiri dengan berkelompok-kelompok?725)"
    },
    {
      "numberInSurah": 38,
      "numberGlobal": 5413,
      "arabic": "اَيَطْمَعُ كُلُّ امْرِئٍ مِّنْهُمْ اَنْ يُّدْخَلَ جَنَّةَ نَعِيْمٍۙ",
      "translation": "Apakah setiap orang dari mereka (orang-orang kafir itu) ingin dimasukkan ke dalam surga yang penuh kenikmatan?"
    },
    {
      "numberInSurah": 39,
      "numberGlobal": 5414,
      "arabic": "كَلَّاۗ اِنَّا خَلَقْنٰهُمْ مِّمَّا يَعْلَمُوْنَ",
      "translation": "Sekali-kali tidak! Sesungguhnya Kami menciptakan mereka dari apa yang mereka ketahui (air mani).726)"
    },
    {
      "numberInSurah": 40,
      "numberGlobal": 5415,
      "arabic": "فَلَآ اُقْسِمُ بِرَبِّ الْمَشٰرِقِ وَالْمَغٰرِبِ اِنَّا لَقٰدِرُوْنَۙ",
      "translation": "Maka, Aku bersumpah dengan Tuhan yang mengatur tempat-tempat terbit dan terbenamnya (matahari, bulan, dan bintang), sesungguhnya Kami benar-benar Maha Kuasa"
    },
    {
      "numberInSurah": 41,
      "numberGlobal": 5416,
      "arabic": "عَلٰٓى اَنْ نُّبَدِّلَ خَيْرًا مِّنْهُمْۙ وَمَا نَحْنُ بِمَسْبُوْقِيْنَ",
      "translation": "untuk mengganti (mereka) dengan (kaum) yang lebih baik daripada mereka. Kami sekali-kali tidak dapat dikalahkan."
    },
    {
      "numberInSurah": 42,
      "numberGlobal": 5417,
      "arabic": "فَذَرْهُمْ يَخُوْضُوْا وَيَلْعَبُوْا حَتّٰى يُلٰقُوْا يَوْمَهُمُ الَّذِيْ يُوْعَدُوْنَۙ",
      "translation": "Maka, biarkanlah mereka tenggelam (dalam kesesatan) dan bermain-main (di dunia) sampai mereka menjumpai hari yang dijanjikan kepada mereka,"
    },
    {
      "numberInSurah": 43,
      "numberGlobal": 5418,
      "arabic": "يَوْمَ يَخْرُجُوْنَ مِنَ الْاَجْدَاثِ سِرَاعًا كَاَنَّهُمْ اِلٰى نُصُبٍ يُّوْفِضُوْنَۙ",
      "translation": "(yaitu) pada hari ketika mereka keluar dari kubur dengan cepat seperti ketika mereka pergi dengan segera menuju berhala-berhala (sewaktu di dunia)."
    },
    {
      "numberInSurah": 44,
      "numberGlobal": 5419,
      "arabic": "خَاشِعَةً اَبْصَارُهُمْ تَرْهَقُهُمْ ذِلَّةٌ  ۗذٰلِكَ الْيَوْمُ الَّذِيْ كَانُوْا يُوْعَدُوْنَ ࣖ",
      "translation": "Pandangan mereka tertunduk (serta) diliputi kehinaan. Itulah hari yang diancamkan kepada mereka."
    }
  ]
}